GammaHeatingControl/__init__.py
GammaHeatingControl/gamma.py
GammaHeatingControl/protocol.py
GammaHeatingControl-0.0.2.dist-info/LICENSE
GammaHeatingControl-0.0.2.dist-info/METADATA
GammaHeatingControl-0.0.2.dist-info/WHEEL
GammaHeatingControl-0.0.2.dist-info/top_level.txt
GammaHeatingControl-0.0.2.dist-info/RECORD
