Metadata-Version: 2.1
Name: GammaHeatingControl
Version: 0.0.2
Summary: A python 3 interface to EBV Gamma Heating Control.
Author-email: Patrick Menschel <menschel.p@posteo.de>
Project-URL: Homepage, https://gitlab.com/menschel/GammaHeatingControl
Project-URL: Bug Tracker, https://gitlab.com/menschel/GammaHeatingControl/issues
Classifier: Programming Language :: Python :: 3
Classifier: Development Status :: 4 - Beta
Classifier: License :: OSI Approved :: GNU General Public License v3 or later (GPLv3+)
Classifier: License :: Free for non-commercial use
Classifier: Intended Audience :: Developers
Classifier: Topic :: Scientific/Engineering
Classifier: Topic :: Software Development :: Embedded Systems
Requires-Python: >=3.10
License-File: LICENSE
Requires-Dist: pyserial
Requires-Dist: crccheck
